__init__.py
example_package_grumbit/__init__.py
example_package_grumbit/example.py
example_package_grumbit-1.0.2.dist-info/LICENSE
example_package_grumbit-1.0.2.dist-info/METADATA
example_package_grumbit-1.0.2.dist-info/WHEEL
example_package_grumbit-1.0.2.dist-info/top_level.txt
example_package_grumbit-1.0.2.dist-info/RECORD
