Metadata-Version: 2.1
Name: example-package-grumbit
Version: 1.0.2
Summary: This is a working example that uses a GitHub actions CI/CD workflow to test, build and upload a Python package to TestPyPi and PyPi.
Author-email: Graham Coster <bitjugglers@gmail.com>
Project-URL: Homepage, https://github.com/grumBit/packaging_tutorial
Project-URL: Bug Tracker, https://github.com/grumBit/packaging_tutorial/issues
Project-URL: Source, https://github.com/grumBit/packaging_tutorial
Classifier: Development Status :: 5 - Production/Stable
Classifier: Programming Language :: Python :: 3
Classifier: License :: OSI Approved :: MIT License
Classifier: Operating System :: OS Independent
Requires-Python: >=3.09
License-File: LICENSE
